hourglass_transformer_pytorch/__init__.py
hourglass_transformer_pytorch/autoregressive_wrapper.py
hourglass_transformer_pytorch/hourglass_transformer_pytorch.py
hourglass_transformer_pytorch-0.0.6.dist-info/LICENSE
hourglass_transformer_pytorch-0.0.6.dist-info/METADATA
hourglass_transformer_pytorch-0.0.6.dist-info/WHEEL
hourglass_transformer_pytorch-0.0.6.dist-info/top_level.txt
hourglass_transformer_pytorch-0.0.6.dist-info/RECORD
